{
"meta":{"test_sets":[],"test_metrics":[],"learn_metrics":[{"best_value":"Min","name":"RMSE"}],"launch_mode":"Train","parameters":"","iteration_count":100,"learn_sets":["learn"],"name":"experiment"},
"iterations":[
{"learn":[14.27330504],"iteration":0,"passed_time":0.03715783129,"remaining_time":3.678625297},
{"learn":[12.55516519],"iteration":1,"passed_time":0.07441752176,"remaining_time":3.646458566},
{"learn":[11.35602282],"iteration":2,"passed_time":0.1055183629,"remaining_time":3.4117604},
{"learn":[10.47385577],"iteration":3,"passed_time":0.1357861447,"remaining_time":3.258867472},
{"learn":[10.04498106],"iteration":4,"passed_time":0.1826741821,"remaining_time":3.470809461},
{"learn":[9.718910079],"iteration":5,"passed_time":0.2273302605,"remaining_time":3.561507414},
{"learn":[9.426578095],"iteration":6,"passed_time":0.2581008271,"remaining_time":3.429053846},
{"learn":[9.250765033],"iteration":7,"passed_time":0.2872723637,"remaining_time":3.303632182},
{"learn":[9.124320602],"iteration":8,"passed_time":0.3245831351,"remaining_time":3.281896144},
{"learn":[8.995175951],"iteration":9,"passed_time":0.3539103658,"remaining_time":3.185193293},
{"learn":[8.912139837],"iteration":10,"passed_time":0.3897809344,"remaining_time":3.153682105},
{"learn":[8.851110137],"iteration":11,"passed_time":0.4281569886,"remaining_time":3.139817916},
{"learn":[8.841073796],"iteration":12,"passed_time":0.4608892506,"remaining_time":3.084412677},
{"learn":[8.771867715],"iteration":13,"passed_time":0.486725107,"remaining_time":2.9898828},
{"learn":[8.72934439],"iteration":14,"passed_time":0.5148600623,"remaining_time":2.917540353},
{"learn":[8.679127176],"iteration":15,"passed_time":0.5474294199,"remaining_time":2.874004454},
{"learn":[8.636345017],"iteration":16,"passed_time":0.5848976628,"remaining_time":2.855676824},
{"learn":[8.58851399],"iteration":17,"passed_time":0.6124891105,"remaining_time":2.79022817},
{"learn":[8.56482463],"iteration":18,"passed_time":0.6481538426,"remaining_time":2.763182171},
{"learn":[8.519219804],"iteration":19,"passed_time":0.6796458827,"remaining_time":2.718583531},
{"learn":[8.496370051],"iteration":20,"passed_time":0.7053041851,"remaining_time":2.653287173},
{"learn":[8.452122216],"iteration":21,"passed_time":0.7383874091,"remaining_time":2.617918996},
{"learn":[8.425499368],"iteration":22,"passed_time":0.7706357247,"remaining_time":2.579954383},
{"learn":[8.385514242],"iteration":23,"passed_time":0.7978736785,"remaining_time":2.526599982},
{"learn":[8.334557497],"iteration":24,"passed_time":0.8270260377,"remaining_time":2.481078113},
{"learn":[8.308306038],"iteration":25,"passed_time":0.8602845101,"remaining_time":2.448502067},
{"learn":[8.283561944],"iteration":26,"passed_time":0.8899767232,"remaining_time":2.406233363},
{"learn":[8.247935435],"iteration":27,"passed_time":0.9146817848,"remaining_time":2.352038875},
{"learn":[8.236043921],"iteration":28,"passed_time":0.9455778265,"remaining_time":2.315035368},
{"learn":[8.199282423],"iteration":29,"passed_time":0.973723117,"remaining_time":2.272020606},
{"learn":[8.176367631],"iteration":30,"passed_time":1.002057163,"remaining_time":2.230385297},
{"learn":[8.157734823],"iteration":31,"passed_time":1.029525983,"remaining_time":2.187742713},
{"learn":[8.149680019],"iteration":32,"passed_time":1.059508484,"remaining_time":2.151123285},
{"learn":[8.101395514],"iteration":33,"passed_time":1.089798534,"remaining_time":2.115491272},
{"learn":[8.022769869],"iteration":34,"passed_time":1.123853062,"remaining_time":2.087155687},
{"learn":[8.009371651],"iteration":35,"passed_time":1.154492732,"remaining_time":2.052431524},
{"learn":[7.937810943],"iteration":36,"passed_time":1.198794459,"remaining_time":2.041190566},
{"learn":[7.888257981],"iteration":37,"passed_time":1.23698886,"remaining_time":2.018244983},
{"learn":[7.845233359],"iteration":38,"passed_time":1.268025031,"remaining_time":1.983321203},
{"learn":[7.83464266],"iteration":39,"passed_time":1.297350194,"remaining_time":1.946025291},
{"learn":[7.814966655],"iteration":40,"passed_time":1.337361934,"remaining_time":1.924496442},
{"learn":[7.771653887],"iteration":41,"passed_time":1.371996582,"remaining_time":1.894661946},
{"learn":[7.72913637],"iteration":42,"passed_time":1.40417701,"remaining_time":1.861350921},
{"learn":[7.722551058],"iteration":43,"passed_time":1.437755868,"remaining_time":1.829871105},
{"learn":[7.690594121],"iteration":44,"passed_time":1.480761009,"remaining_time":1.809819011},
{"learn":[7.646519538],"iteration":45,"passed_time":1.509751397,"remaining_time":1.772316858},
{"learn":[7.575246269],"iteration":46,"passed_time":1.54885714,"remaining_time":1.746583583},
{"learn":[7.538160187],"iteration":47,"passed_time":1.578646224,"remaining_time":1.710200076},
{"learn":[7.497638517],"iteration":48,"passed_time":1.603625169,"remaining_time":1.669079258},
{"learn":[7.482347464],"iteration":49,"passed_time":1.631948965,"remaining_time":1.631948965},
{"learn":[7.4024869],"iteration":50,"passed_time":1.67575127,"remaining_time":1.610035534},
{"learn":[7.363942931],"iteration":51,"passed_time":1.715070207,"remaining_time":1.583141729},
{"learn":[7.315071131],"iteration":52,"passed_time":1.753207236,"remaining_time":1.554730945},
{"learn":[7.272046766],"iteration":53,"passed_time":1.793321461,"remaining_time":1.527644208},
{"learn":[7.262686975],"iteration":54,"passed_time":1.839504781,"remaining_time":1.505049366},
{"learn":[7.227060795],"iteration":55,"passed_time":1.884254933,"remaining_time":1.480486018},
{"learn":[7.189539321],"iteration":56,"passed_time":1.928746117,"remaining_time":1.455019001},
{"learn":[7.182674349],"iteration":57,"passed_time":1.963676621,"remaining_time":1.421972726},
{"learn":[7.173430353],"iteration":58,"passed_time":1.998381372,"remaining_time":1.388705699},
{"learn":[7.141995781],"iteration":59,"passed_time":2.043503678,"remaining_time":1.362335785},
{"learn":[7.10096807],"iteration":60,"passed_time":2.078473977,"remaining_time":1.328860411},
{"learn":[7.030363017],"iteration":61,"passed_time":2.113186486,"remaining_time":1.295178814},
{"learn":[6.95772947],"iteration":62,"passed_time":2.151796984,"remaining_time":1.263753785},
{"learn":[6.919637991],"iteration":63,"passed_time":2.192254744,"remaining_time":1.233143294},
{"learn":[6.890865637],"iteration":64,"passed_time":2.234298035,"remaining_time":1.203083557},
{"learn":[6.876724156],"iteration":65,"passed_time":2.267476542,"remaining_time":1.168093976},
{"learn":[6.850209723],"iteration":66,"passed_time":2.301794554,"remaining_time":1.133719706},
{"learn":[6.791976372],"iteration":67,"passed_time":2.340756137,"remaining_time":1.1015323},
{"learn":[6.726405366],"iteration":68,"passed_time":2.378809868,"remaining_time":1.068740665},
{"learn":[6.718817328],"iteration":69,"passed_time":2.418636963,"remaining_time":1.036558698},
{"learn":[6.681936307],"iteration":70,"passed_time":2.459157487,"remaining_time":1.004444607},
{"learn":[6.668830729],"iteration":71,"passed_time":2.495807652,"remaining_time":0.9705918648},
{"learn":[6.663319089],"iteration":72,"passed_time":2.539379096,"remaining_time":0.9392224055},
{"learn":[6.638761959],"iteration":73,"passed_time":2.566653046,"remaining_time":0.9017970162},
{"learn":[6.601194114],"iteration":74,"passed_time":2.596129002,"remaining_time":0.8653763341},
{"learn":[6.596787208],"iteration":75,"passed_time":2.621897363,"remaining_time":0.8279675882},
{"learn":[6.567717785],"iteration":76,"passed_time":2.683321123,"remaining_time":0.8015115041},
{"learn":[6.561506726],"iteration":77,"passed_time":2.719375255,"remaining_time":0.767003277},
{"learn":[6.528755828],"iteration":78,"passed_time":2.771672762,"remaining_time":0.7367737721},
{"learn":[6.511130361],"iteration":79,"passed_time":2.796908265,"remaining_time":0.6992270662},
{"learn":[6.487833886],"iteration":80,"passed_time":2.844519517,"remaining_time":0.6672329732},
{"learn":[6.456643086],"iteration":81,"passed_time":2.870854261,"remaining_time":0.6301875206},
{"learn":[6.402318823],"iteration":82,"passed_time":2.907781296,"remaining_time":0.5955696631},
{"learn":[6.362556362],"iteration":83,"passed_time":2.934952817,"remaining_time":0.5590386317},
{"learn":[6.355963177],"iteration":84,"passed_time":2.970462323,"remaining_time":0.5241992335},
{"learn":[6.327041662],"iteration":85,"passed_time":3.021922842,"remaining_time":0.4919409277},
{"learn":[6.321288181],"iteration":86,"passed_time":3.050210516,"remaining_time":0.4557785829},
{"learn":[6.272783051],"iteration":87,"passed_time":3.09022173,"remaining_time":0.4213938723},
{"learn":[6.22374545],"iteration":88,"passed_time":3.128237975,"remaining_time":0.3866361542},
{"learn":[6.199982263],"iteration":89,"passed_time":3.164304767,"remaining_time":0.3515894185},
{"learn":[6.173652676],"iteration":90,"passed_time":3.19827114,"remaining_time":0.3163125303},
{"learn":[6.12892918],"iteration":91,"passed_time":3.240425545,"remaining_time":0.2817761344},
{"learn":[6.103304187],"iteration":92,"passed_time":3.297882861,"remaining_time":0.2482277422},
{"learn":[6.067443105],"iteration":93,"passed_time":3.3350606,"remaining_time":0.2128762085},
{"learn":[6.032851287],"iteration":94,"passed_time":3.363686336,"remaining_time":0.177036123},
{"learn":[5.981632646],"iteration":95,"passed_time":3.406781674,"remaining_time":0.1419492364},
{"learn":[5.949150316],"iteration":96,"passed_time":3.447311472,"remaining_time":0.1066178806},
{"learn":[5.905622203],"iteration":97,"passed_time":3.504646213,"remaining_time":0.07152339211},
{"learn":[5.885745355],"iteration":98,"passed_time":3.541255692,"remaining_time":0.03577025951},
{"learn":[5.833664371],"iteration":99,"passed_time":3.591575316,"remaining_time":0}
]}